django_session_controller/__init__.py
django_session_controller/admin.py
django_session_controller/apps.py
django_session_controller/middleware.py
django_session_controller/models.py
django_session_controller/session_decorators.py
django_session_controller/session_signals.py
django_session_controller/setup.py
django_session_controller/migrations/__init__.py
django_session_controller-0.1.dist-info/LICENSE
django_session_controller-0.1.dist-info/METADATA
django_session_controller-0.1.dist-info/WHEEL
django_session_controller-0.1.dist-info/top_level.txt
django_session_controller-0.1.dist-info/RECORD
