Metadata-Version: 2.1
Name: django-session-controller
Version: 0.1
Summary: A Configurable Session Controller
Home-page: https://github.com/viswanathreddy/django-session-controller
Author: viswanath,naveen,sibasish
Author-email: visu.sanepalle@gmail.com
License: MIT License
Platform: UNKNOWN
Classifier: Environment :: Web Environment
Classifier: Framework :: Django
Classifier: Intended Audience :: Developers
Classifier: License :: OSI Approved :: MIT License
Classifier: Operating System :: OS Independent
Classifier: Programming Language :: Python
Classifier: Programming Language :: Python :: 3.5
Classifier: Programming Language :: Python :: 3.6
Classifier: Topic :: Internet :: WWW/HTTP
Classifier: Topic :: Internet :: WWW/HTTP :: Dynamic Content
